cdktf_cdktf_provider_boundary/__init__.py
cdktf_cdktf_provider_boundary/py.typed
cdktf_cdktf_provider_boundary/_jsii/__init__.py
cdktf_cdktf_provider_boundary/_jsii/provider-boundary@10.1.1.jsii.tgz
cdktf_cdktf_provider_boundary/account/__init__.py
cdktf_cdktf_provider_boundary/account_ldap/__init__.py
cdktf_cdktf_provider_boundary/account_oidc/__init__.py
cdktf_cdktf_provider_boundary/account_password/__init__.py
cdktf_cdktf_provider_boundary/alias_target/__init__.py
cdktf_cdktf_provider_boundary/auth_method/__init__.py
cdktf_cdktf_provider_boundary/auth_method_ldap/__init__.py
cdktf_cdktf_provider_boundary/auth_method_oidc/__init__.py
cdktf_cdktf_provider_boundary/auth_method_password/__init__.py
cdktf_cdktf_provider_boundary/credential_json/__init__.py
cdktf_cdktf_provider_boundary/credential_library_vault/__init__.py
cdktf_cdktf_provider_boundary/credential_library_vault_ssh_certificate/__init__.py
cdktf_cdktf_provider_boundary/credential_ssh_private_key/__init__.py
cdktf_cdktf_provider_boundary/credential_store_static/__init__.py
cdktf_cdktf_provider_boundary/credential_store_vault/__init__.py
cdktf_cdktf_provider_boundary/credential_username_password/__init__.py
cdktf_cdktf_provider_boundary/data_boundary_account/__init__.py
cdktf_cdktf_provider_boundary/data_boundary_auth_method/__init__.py
cdktf_cdktf_provider_boundary/data_boundary_group/__init__.py
cdktf_cdktf_provider_boundary/data_boundary_scope/__init__.py
cdktf_cdktf_provider_boundary/data_boundary_user/__init__.py
cdktf_cdktf_provider_boundary/group/__init__.py
cdktf_cdktf_provider_boundary/host/__init__.py
cdktf_cdktf_provider_boundary/host_catalog/__init__.py
cdktf_cdktf_provider_boundary/host_catalog_plugin/__init__.py
cdktf_cdktf_provider_boundary/host_catalog_static/__init__.py
cdktf_cdktf_provider_boundary/host_set/__init__.py
cdktf_cdktf_provider_boundary/host_set_plugin/__init__.py
cdktf_cdktf_provider_boundary/host_set_static/__init__.py
cdktf_cdktf_provider_boundary/host_static/__init__.py
cdktf_cdktf_provider_boundary-10.1.1.dist-info/LICENSE
cdktf_cdktf_provider_boundary-10.1.1.dist-info/METADATA
cdktf_cdktf_provider_boundary-10.1.1.dist-info/WHEEL
cdktf_cdktf_provider_boundary-10.1.1.dist-info/top_level.txt
cdktf_cdktf_provider_boundary-10.1.1.dist-info/RECORD
